<?xml version="1.0" encoding="UTF-8"?>
<databaseChangeLog
        xmlns="http://www.liquibase.org/xml/ns/dbchangelog/1.9"
        xmlns:xsi="http://www.w3.org/2001/XMLSchema-instance"
        xsi:schemaLocation="http://www.liquibase.org/xml/ns/dbchangelog/1.9
                      http://www.liquibase.org/xml/ns/dbchangelog/dbchangelog-1.9.xsd">

    <changeSet  author="ramona" id="changelog-1.0">
        <createTable tableName="ZTH_EMPLOYEE_RAMONA">
             <column name="PRES_ID" type="NUMBER" autoIncrement="true">
                     <constraints primaryKey="true" nullable="false"/>
             </column>
             <column name="FIRST_NAME" type="VARCHAR(40)" autoIncrement="true">
             </column>
             <column name="LAST_NAME" type="VARCHAR(40)" autoIncrement="true">
             </column>
             <column name="EMAIL" type="VARCHAR(40)" autoIncrement="true">
                 <constraints nullable="false"/>
             </column>
             <column name="PHONE_NUMBER" type="VARCHAR(25)" autoIncrement="true">
                <constraints nullable="false"/>
             </column>
             <column name="ADDRESS_NUMBER" type="NUMBER(6)" autoIncrement="true">
                <constraints nullable="false"/>
             </column>
        </createTable>
        </changeSet>

    </databaseChangeLog>

